{"cameraMode":{"drawMode":0,"name":"Shaded","section":"Shading Mode"},"sceneLighting":true,"audioPlay":false,"sceneViewState":{"m_AlwaysRefresh":false,"showFog":true,"showSkybox":true,"showFlares":true,"showImageEffects":true,"showParticleSystems":true,"showVisualEffectGraphs":true,"m_FxEnabled":true},"in2DMode":false,"pivot":{"x":-10.853870391845704,"y":17.187314987182618,"z":-19.05768585205078},"rotation":{"x":0.26775580644607546,"y":-0.026883423328399659,"z":0.007449098862707615,"w":0.9631435871124268},"size":21.462657928466798,"orthographic":false}